collective.volto.secondarymenu-2.0.0-py3.11-nspkg.pth
collective/volto/secondarymenu/__init__.py
collective/volto/secondarymenu/configure.zcml
collective/volto/secondarymenu/interfaces.py
collective/volto/secondarymenu/permissions.zcml
collective/volto/secondarymenu/setuphandlers.py
collective/volto/secondarymenu/testing.py
collective/volto/secondarymenu/browser/__init__.py
collective/volto/secondarymenu/browser/configure.zcml
collective/volto/secondarymenu/browser/controlpanel.py
collective/volto/secondarymenu/locales/README.rst
collective/volto/secondarymenu/locales/__init__.py
collective/volto/secondarymenu/locales/collective.volto.secondarymenu.pot
collective/volto/secondarymenu/locales/update.py
collective/volto/secondarymenu/locales/update.sh
collective/volto/secondarymenu/locales/es/LC_MESSAGES/collective.volto.secondarymenu.po
collective/volto/secondarymenu/locales/it/LC_MESSAGES/collective.volto.secondarymenu.po
collective/volto/secondarymenu/profiles/default/browserlayer.xml
collective/volto/secondarymenu/profiles/default/controlpanel.xml
collective/volto/secondarymenu/profiles/default/metadata.xml
collective/volto/secondarymenu/profiles/default/registry.xml
collective/volto/secondarymenu/profiles/default/rolemap.xml
collective/volto/secondarymenu/profiles/uninstall/browserlayer.xml
collective/volto/secondarymenu/profiles/uninstall/controlpanel.xml
collective/volto/secondarymenu/profiles/uninstall/registry.xml
collective/volto/secondarymenu/restapi/__init__.py
collective/volto/secondarymenu/restapi/configure.zcml
collective/volto/secondarymenu/restapi/deserializer/__init__.py
collective/volto/secondarymenu/restapi/deserializer/configure.zcml
collective/volto/secondarymenu/restapi/deserializer/secondary_menu.py
collective/volto/secondarymenu/restapi/secondary_menu/__init__.py
collective/volto/secondarymenu/restapi/secondary_menu/configure.zcml
collective/volto/secondarymenu/restapi/secondary_menu/get.py
collective_volto_secondarymenu-2.0.0.dist-info/LICENSE.GPL
collective_volto_secondarymenu-2.0.0.dist-info/LICENSE.rst
collective_volto_secondarymenu-2.0.0.dist-info/METADATA
collective_volto_secondarymenu-2.0.0.dist-info/WHEEL
collective_volto_secondarymenu-2.0.0.dist-info/entry_points.txt
collective_volto_secondarymenu-2.0.0.dist-info/namespace_packages.txt
collective_volto_secondarymenu-2.0.0.dist-info/top_level.txt
collective_volto_secondarymenu-2.0.0.dist-info/RECORD
